timing/__init__.py
timing/_version.py
timing/cache.py
timing/config.py
timing/group.py
timing/py.typed
timing/timing.py
timing/utils.py
timing-0.6.0.dist-info/licenses/LICENSE
timing-0.6.0.dist-info/licenses/NOTICE
timing-0.6.0.dist-info/METADATA
timing-0.6.0.dist-info/WHEEL
timing-0.6.0.dist-info/top_level.txt
timing-0.6.0.dist-info/RECORD
