Metadata-Version: 2.4
Name: timing
Version: 0.6.0
Summary: Simplify logging of timings of selected parts of an application.
Home-page: https://github.com/mbdevpl/timing
Download-URL: 
Author: Mateusz Bysiek
Author-email: mateusz.bysiek@gmail.com
Maintainer: Mateusz Bysiek
Maintainer-email: mateusz.bysiek@gmail.com
License-Expression: Apache-2.0
Keywords: timing,timer,time measurement,profiling,reproducibility
Classifier: Development Status :: 2 - Pre-Alpha
Classifier: Environment :: Console
Classifier: Intended Audience :: Developers
Classifier: Intended Audience :: Science/Research
Classifier: Natural Language :: English
Classifier: Operating System :: MacOS
Classifier: Operating System :: Microsoft :: Windows
Classifier: Operating System :: POSIX :: Linux
Classifier: Programming Language :: Python :: 3.11
Classifier: Programming Language :: Python :: 3.12
Classifier: Programming Language :: Python :: 3.13
Classifier: Programming Language :: Python :: 3 :: Only
Classifier: Topic :: Scientific/Engineering
Classifier: Topic :: System :: Benchmark
Classifier: Topic :: System :: Logging
Classifier: Typing :: Typed
Requires-Python: >=3.11
License-File: LICENSE
License-File: NOTICE
Requires-Dist: numpy~=2.2
Requires-Dist: version-query~=1.6
Dynamic: author
Dynamic: author-email
Dynamic: classifier
Dynamic: description
Dynamic: description-content-type
Dynamic: home-page
Dynamic: keywords
Dynamic: license-file
Dynamic: license-expression
Dynamic: maintainer
Dynamic: maintainer-email
Dynamic: requires-dist
Dynamic: requires-python
Dynamic: summary
